kirami_plugin_sentry-0.1.0.dist-info/METADATA
kirami_plugin_sentry-0.1.0.dist-info/WHEEL
kirami_plugin_sentry-0.1.0.dist-info/licenses/LICENSE
kirami_plugin_sentry/__init__.py
kirami_plugin_sentry/config.py
kirami_plugin_sentry/hook.py
kirami_plugin_sentry/plugin.py
kirami_plugin_sentry-0.1.0.dist-info/RECORD
