Metadata-Version: 2.1
Name: kirami-plugin-sentry
Version: 0.1.0
Summary: 在 Sentry.io 上进行 KiramiBot 服务日志查看、错误处理，以及群聊消息提醒
Author-Email: Komorebi <mute231010@gmail.com>
License: MIT
Requires-Python: >=3.10
Requires-Dist: kiramibot>=0.3.2
Requires-Dist: sentry-sdk>=1.31.0
